{
    "numCorrect": 7,
    "prize": "£550",
    "questionCount": 12,
    "questions": [
        {
            "answers": {
                "A": "Duke of Durham",
                "B": "Elephant",
                "C": "Rolls Royce"
            },
            "category": "Educational",
            "correct": "B",
            "prediction": {
                "answer": "B",
                "confidence": {
                    "A": "0%",
                    "B": "90%",
                    "C": "9%"
                }
            },
            "question": "A useless or unwanted possession is described as a white what?",
            "questionId": 35924,
            "questionNumber": 1
        },
        {
            "answers": {
                "A": "Mayfair",
                "B": "Mayday! Mayday!",
                "C": "Maybe a bit unfair"
            },
            "category": "Games",
            "correct": "A",
            "prediction": {
                "answer": "A",
                "confidence": {
                    "A": "96%",
                    "B": "3%",
                    "C": "0%"
                }
            },
            "question": "What is the name of the most expensive dark blue property in the British version of Monopoly?",
            "questionId": 35925,
            "questionNumber": 2
        },
        {
            "answers": {
                "A": "£100",
                "B": "£30",
                "C": "£50"
            },
            "category": "Business",
            "correct": "B",
            "prediction": {
                "answer": "C",
                "confidence": {
                    "A": "28%",
                    "B": "29%",
                    "C": "42%"
                }
            },
            "question": "What did the limit on contactless card payments climb to in September 2015?",
            "questionId": 35926,
            "questionNumber": 3
        },
        {
            "answers": {
                "A": "Liam Neeson",
                "B": "Ewan McGregor",
                "C": "Alec Guinness"
            },
            "category": "Movies",
            "correct": "B",
            "prediction": {
                "answer": "B",
                "confidence": {
                    "A": "12%",
                    "B": "78%",
                    "C": "9%"
                }
            },
            "question": "Which actor's brother is a former RAF pilot with the call sign “Obi-Two”?",
            "questionId": 35951,
            "questionNumber": 4
        },
        {
            "answers": {
                "A": "Liverpool",
                "B": "Portsmouth",
                "C": "Southampton"
            },
            "category": "History",
            "correct": "A",
            "prediction": {
                "answer": "A",
                "confidence": {
                    "A": "79%",
                    "B": "8%",
                    "C": "11%"
                }
            },
            "question": "Which of these cities was \"The Lusitania\" heading to when it sank?",
            "questionId": 35952,
            "questionNumber": 5
        },
        {
            "answers": {
                "A": "Manic Street Preachers",
                "B": "Stereophonics",
                "C": "Super Furry Animals"
            },
            "category": "Music",
            "correct": "B",
            "prediction": {
                "answer": "A",
                "confidence": {
                    "A": "51%",
                    "B": "34%",
                    "C": "14%"
                }
            },
            "question": "Which of these bands provided live music at Wayne Rooney's wedding to Colleen?",
            "questionId": 35953,
            "questionNumber": 6
        },
        {
            "answers": {
                "A": "Jack Nicklaus",
                "B": "Tiger Woods",
                "C": "Sergio Garcia"
            },
            "category": "Sports",
            "correct": "C",
            "prediction": {
                "answer": "C",
                "confidence": {
                    "A": "22%",
                    "B": "18%",
                    "C": "58%"
                }
            },
            "question": "Which of these golfers named his first child after a hole at the Augusta golf course?",
            "questionId": 35954,
            "questionNumber": 7
        },
        {
            "answers": {
                "A": "Mabel",
                "B": "Grog",
                "C": "Grip"
            },
            "category": "Nature",
            "correct": "C",
            "prediction": {
                "answer": "C",
                "confidence": {
                    "A": "17%",
                    "B": "35%",
                    "C": "46%"
                }
            },
            "question": "At the end of World War II, what was the name of the only raven left at the Tower of London?",
            "questionId": 35955,
            "questionNumber": 8
        },
        {
            "answers": {
                "A": "Oldboy",
                "B": "The Lake House",
                "C": "The Departed"
            },
            "category": "Movies",
            "correct": "C",
            "prediction": {
                "answer": "B",
                "confidence": {
                    "A": "48%",
                    "B": "20%",
                    "C": "30%"
                }
            },
            "question": "Which of these American movies is NOT a remake of a South Korean movie?",
            "questionId": 35956,
            "questionNumber": 9
        },
        {
            "answers": {
                "A": "Caribbean lily",
                "B": "Ascension fern",
                "C": "Hawaiian hibiscus"
            },
            "category": "Nature",
            "correct": "B",
            "prediction": {
                "answer": "C",
                "confidence": {
                    "A": "0%",
                    "B": "0%",
                    "C": "100%"
                }
            },
            "question": "Which of these plants was found on a volcanic island after it was presumed extinct?",
            "questionId": 35957,
            "questionNumber": 10
        },
        {
            "answers": {
                "A": "Lolita",
                "B": "A Clockwork Orange",
                "C": "The Satanic Verses"
            },
            "category": "Literature ",
            "correct": "A",
            "prediction": {
                "answer": "C",
                "confidence": {
                    "A": "27%",
                    "B": "21%",
                    "C": "51%"
                }
            },
            "question": "Which of these literary texts was banned in the U.K.?",
            "questionId": 35958,
            "questionNumber": 11
        },
        {
            "answers": {
                "A": "India / Sri Lanka",
                "B": "Singapore / Malaysia",
                "C": "Cuba / The Bahamas"
            },
            "category": "History",
            "correct": "A",
            "prediction": {
                "answer": "A",
                "confidence": {
                    "A": "39%",
                    "B": "27%",
                    "C": "32%"
                }
            },
            "question": "An 18th-century English MP lends his name to the strait between which two countries?",
            "questionId": 35959,
            "questionNumber": 12
        }
    ],
    "showId": 4456,
    "ts": "2018-04-17T14:01:03.736Z"
}