{
    "numCorrect": 6,
    "prize": "£550",
    "questionCount": 12,
    "questions": [
        {
            "answers": {
                "A": "The Nile",
                "B": "Niagara Falls",
                "C": "River Severn"
            },
            "category": "Geography",
            "correct": "C",
            "prediction": {
                "answer": "C",
                "confidence": {
                    "A": "19%",
                    "B": "19%",
                    "C": "61%"
                }
            },
            "question": "Which of the following is Britain’s longest river?",
            "questionId": 37356,
            "questionNumber": 1
        },
        {
            "answers": {
                "A": "Jet lag",
                "B": "Jet wash",
                "C": "Jethro"
            },
            "category": "Educational",
            "correct": "A",
            "prediction": {
                "answer": "A",
                "confidence": {
                    "A": "88%",
                    "B": "0%",
                    "C": "11%"
                }
            },
            "question": "A feeling of extreme tiredness after a long flight is known as what?",
            "questionId": 37357,
            "questionNumber": 2
        },
        {
            "answers": {
                "A": "Elm Street",
                "B": "Wisteria Lane",
                "C": "Sesame Street"
            },
            "category": "TV",
            "correct": "B",
            "prediction": {
                "answer": "B",
                "confidence": {
                    "A": "3%",
                    "B": "88%",
                    "C": "7%"
                }
            },
            "question": "Which of these is the setting for “Desperate Housewives”?",
            "questionId": 37359,
            "questionNumber": 3
        },
        {
            "answers": {
                "A": "Heathen",
                "B": "The Next Day",
                "C": "Blackstar"
            },
            "category": "Music",
            "correct": "C",
            "prediction": {
                "answer": "C",
                "confidence": {
                    "A": "5%",
                    "B": "40%",
                    "C": "54%"
                }
            },
            "question": "Which of these is the title of David Bowie's final album?",
            "questionId": 37361,
            "questionNumber": 4
        },
        {
            "answers": {
                "A": "David Attenborough",
                "B": "Helen Mirren",
                "C": "Cher"
            },
            "category": "Entertainment",
            "correct": "C",
            "prediction": {
                "answer": "A",
                "confidence": {
                    "A": "14%",
                    "B": "54%",
                    "C": "31%"
                }
            },
            "question": "Which of these celebrities does NOT have a carnivorous plant named after them?",
            "questionId": 37364,
            "questionNumber": 5
        },
        {
            "answers": {
                "A": "The Panama hat",
                "B": "The Brazilian wax",
                "C": "The Dutch auction"
            },
            "category": "Educational",
            "correct": "B",
            "prediction": {
                "answer": "A",
                "confidence": {
                    "A": "46%",
                    "B": "26%",
                    "C": "27%"
                }
            },
            "question": "Which of the following was invented in New York?",
            "questionId": 37367,
            "questionNumber": 6
        },
        {
            "answers": {
                "A": "George Eliot",
                "B": "J.R.R Tolkien",
                "C": "Edgar Allan Poe"
            },
            "category": "Literature ",
            "correct": "A",
            "prediction": {
                "answer": "B",
                "confidence": {
                    "A": "22%",
                    "B": "42%",
                    "C": "34%"
                }
            },
            "question": "Which of these author's names is a pseudonym?",
            "questionId": 37369,
            "questionNumber": 7
        },
        {
            "answers": {
                "A": "An elephant",
                "B": "Stuffed swans",
                "C": "A ventriloquist"
            },
            "category": "History",
            "correct": "A",
            "prediction": {
                "answer": "A",
                "confidence": {
                    "A": "98%",
                    "B": "0%",
                    "C": "1%"
                }
            },
            "question": "What gift did the King of France once send Henry III?",
            "questionId": 37371,
            "questionNumber": 8
        },
        {
            "answers": {
                "A": "Lordi",
                "B": "Dana International",
                "C": "Conchita Wurst"
            },
            "category": "Entertainment",
            "correct": "C",
            "prediction": {
                "answer": "C",
                "confidence": {
                    "A": "23%",
                    "B": "36%",
                    "C": "40%"
                }
            },
            "question": "Which  Eurovision act’s victory was followed by their country failing to win any points the next year?",
            "questionId": 37372,
            "questionNumber": 9
        },
        {
            "answers": {
                "A": "This American Life",
                "B": "Reply-All",
                "C": "Serial"
            },
            "category": "Tech",
            "correct": "B",
            "prediction": {
                "answer": "A",
                "confidence": {
                    "A": "54%",
                    "B": "4%",
                    "C": "41%"
                }
            },
            "question": "Which podcast's subjects have included boring Facebook groups and hacked Uber accounts?",
            "questionId": 37373,
            "questionNumber": 10
        },
        {
            "answers": {
                "A": "Baker",
                "B": "Comedian",
                "C": "Undertaker"
            },
            "category": "Science ",
            "correct": "B",
            "prediction": {
                "answer": "A",
                "confidence": {
                    "A": "51%",
                    "B": "23%",
                    "C": "24%"
                }
            },
            "question": "What was the profession of the person credited with discovering the Great White Spot on Saturn?",
            "questionId": 37374,
            "questionNumber": 11
        },
        {
            "answers": {
                "A": "Eric Cantona",
                "B": "David Ginola",
                "C": "Vinnie Jones"
            },
            "category": "Movies",
            "correct": "B",
            "prediction": {
                "answer": "A",
                "confidence": {
                    "A": "43%",
                    "B": "13%",
                    "C": "42%"
                }
            },
            "question": "Which of these footballers played an army sniper in a 2006 World War II film?",
            "questionId": 37375,
            "questionNumber": 12
        }
    ],
    "showId": 4594,
    "ts": "2018-04-25T13:58:37.515Z"
}