{
    "numCorrect": 9,
    "prize": "£1,000",
    "questionCount": 12,
    "questions": [
        {
            "answers": {
                "A": "Zorro",
                "B": "Superman",
                "C": "Lightning"
            },
            "category": "Language",
            "correct": "C",
            "prediction": {
                "answer": "C",
                "confidence": {
                    "A": "0%",
                    "B": "0%",
                    "C": "99%"
                }
            },
            "question": "According to the saying, what is commonly thought to “not strike twice”?",
            "questionId": 53070,
            "questionNumber": 1
        },
        {
            "answers": {
                "A": "Y",
                "B": "Z",
                "C": "A"
            },
            "category": "Language",
            "correct": "A",
	    "prediction": {
                "answer": "C",
                "confidence": {
                    "A": "19%",
                    "B": "12%",
                    "C": "67%"
                }
            },
            "question": "Which of the following is the penultimate letter of the English alphabet?",
            "questionId": 53071,
            "questionNumber": 2
        },
        {
            "answers": {
                "A": "December",
                "B": "May",
                "C": "January"
            },
            "category": "Culture",
            "correct": "B",
            "prediction": {
                "answer": "B",
                "confidence": {
                    "A": "6%",
                    "B": "86%",
                    "C": "6%"
                }
            },
            "question": "The holiday known as Cinco de Mayo is celebrated in which month?",
            "questionId": 53072,
            "questionNumber": 3
        },
        {
            "answers": {
                "A": "Black",
                "B": "Blue",
                "C": "Yellow"
            },
            "category": "Tech",
            "correct": "B",
            "prediction": {
                "answer": "B",
                "confidence": {
                    "A": "10%",
                    "B": "77%",
                    "C": "11%"
                }
            },
            "question": "Which of these is a primary brand colour for Facebook and Twitter?",
            "questionId": 53073,
            "questionNumber": 4
        },
        {
            "answers": {
                "A": "Line ball",
                "B": "Square ball",
                "C": "Dot ball"
            },
            "category": "Sports",
            "correct": "C",
            "prediction": {
                "answer": "C",
                "confidence": {
                    "A": "4%",
                    "B": "12%",
                    "C": "82%"
                }
            },
            "question": "In cricket, what is the name given to a delivery without any runs scored off it?",
            "questionId": 53074,
            "questionNumber": 5
        },
        {
            "answers": {
                "A": "Stink badger",
                "B": "Stink otter",
                "C": "Stink raccoon"
            },
            "category": "Nature",
            "correct": "A",
            "prediction": {
                "answer": "A",
                "confidence": {
                    "A": "100%",
                    "B": "0%",
                    "C": "0%"
                }
            },
            "question": "Which of these is a member of the skunk family, native to South East Asia?",
            "questionId": 53075,
            "questionNumber": 6
        },
        {
            "answers": {
                "A": "DuckTales",
                "B": "Scooby-Doo",
                "C": "The Jetsons"
            },
            "category": "TV",
            "correct": "A",
            "prediction": {
                "answer": "A",
                "confidence": {
                    "A": "6%",
                    "B": "59%",
                    "C": "33%"
                }
            },
            "question": "Which of these was NOT a Hanna-Barbera creation?",
            "questionId": 53076,
            "questionNumber": 7
        },
        {
            "answers": {
                "A": "Colombia",
                "B": "Spain",
                "C": "Mexico"
            },
            "category": "History",
            "correct": "C",
            "prediction": {
                "answer": "C",
                "confidence": {
                    "A": "76%",
                    "B": "12%",
                    "C": "10%"
                }
            },
            "question": "From which of these countries does Panama NOT celebrate independence?",
            "questionId": 53077,
            "questionNumber": 8
        },
        {
            "answers": {
                "A": "Kenneth Branagh",
                "B": "Vanessa Redgrave",
                "C": "Michael Caine"
            },
            "category": "Movies",
            "correct": "A",
            "prediction": {
                "answer": "C",
                "confidence": {
                    "A": "34%",
                    "B": "51%",
                    "C": "14%"
                }
            },
            "question": "Which of these figures has NOT received a BAFTA Fellowship Award?",
            "questionId": 53078,
            "questionNumber": 9
        },
        {
            "answers": {
                "A": "Brighter than the sun",
                "B": "Older than the sun",
                "C": "Hotter than the sun"
            },
            "category": "Science",
            "correct": "A",
            "prediction": {
                "answer": "A",
                "confidence": {
                    "A": "80%",
                    "B": "5%",
                    "C": "13%"
                }
            },
            "question": "Visible in Earth's night skies, which of the following is true about the giant star Betelgeuse?",
            "questionId": 53079,
            "questionNumber": 10
        },
        {
            "answers": {
                "A": "Maul",
                "B": "Boba Fett",
                "C": "Enfys Nest"
            },
            "category": "Movies",
            "correct": "B",
            "prediction": {
                "answer": "C",
                "confidence": {
                    "A": "45%",
                    "B": "45%",
                    "C": "9%"
                }
            },
            "question": "Which of these “Star Wars” characters does NOT feature in the 2018 “Solo” movie?",
            "questionId": 53080,
            "questionNumber": 11
        },
        {
            "answers": {
                "A": "North Korea",
                "B": "Afghanistan",
                "C": "Norway"
            },
            "category": "Geography",
            "correct": "B",
            "prediction": {
                "answer": "B",
                "confidence": {
                    "A": "36%",
                    "B": "26%",
                    "C": "36%"
                }
            },
            "question": "Which of these countries does NOT share a land border with Russia?",
            "questionId": 53081,
            "questionNumber": 12
        }
    ],
    "showId": 6268,
    "ts": "2018-07-20T14:02:44.588Z"
}
